{
  "name": "Peter Becker",
  "age": 39,
  "address": {
    "street": "Tisu Road",
    "city": "Houcije",
    "state": "NC",
    "zip": "15057"
  },
  "contact": {
    "phone": "(833) 938-8847",
    "servicePhone": "800186592"
  },
  "birthday": "1973-01-16T23:31:59.126Z",
  "ip": "24.95.151.128",
  "foo": "bar",
  "profile": {
    "about": "Ug teikvev towihhe gasagco vedme janafu dedatuop ictiuk ifuha dovhusmu ga meduduk ovavijfe jamirju. Jer puve mawru cafkam tigdil kob rivfa uhziug jatog be ehe luzis pomvo zusvaho. Iko upni birtasma donfas bihe ejara ok gagpovfac vivupsiz be agahalu or piozij bokaweep wezhocire. Razu odreg ih til neluw ko suhhik focviza bep ale pec kon pacganko ce cip pil zosor. Tigwusva jijlew kimim hiiwi azik oleilahi edduw lo lodev jiti eju hiwef li.",
    "bio": "Se panirma ce oto gatezo ojedo kostapoh muc dihka ij val vebanzot lugpazav zav hiwku fuguf. Oggo cebkac jizucmuz vi taradup uzuketij tamhi socfoz rupejubu baggup mam za nuc kotjif. Esahagfa ofimes nosawec himnuzas eko ta feowelez sigawoovi se rafnokej wohija lelkiz notbaip suv. Bo adoje goruk os nopvan gobigu tel idesi porrodmos welucu nijgew hir liah sa dalleaha kabidzu bokepi. Otpuplup gelrok wu pesafen mebliz tiviada heninen ru fad ru iteumo nowe jebfu guaswuh re lotatoj pabsiuz walotsas."
  },
  "apiKey": "08b00d11f2e57725741fe0a8ed3fb9a118a9010beae5a2e38821e1336c954b90",
  "currency": {
    "code": "THB",
    "name": "Thailand Baht"
  }
}